tiny_web_crawler/__init__.py
tiny_web_crawler/core/__init__.py
tiny_web_crawler/core/spider.py
tiny_web_crawler/core/spider_settings.py
tiny_web_crawler/logging.py
tiny_web_crawler/middlewares/__init__.py
tiny_web_crawler/networking/__init__.py
tiny_web_crawler/networking/fetcher.py
tiny_web_crawler/networking/formatter.py
tiny_web_crawler/networking/robots_txt.py
tiny_web_crawler/networking/validator.py
tiny_web_crawler/webdrivers/__init__.py
tiny_web_crawler-0.5.0.dist-info/LICENSE
tiny_web_crawler-0.5.0.dist-info/METADATA
tiny_web_crawler-0.5.0.dist-info/WHEEL
tiny_web_crawler-0.5.0.dist-info/entry_points.txt
tiny_web_crawler-0.5.0.dist-info/RECORD
