Metadata-Version: 2.1
Name: tiny-web-crawler
Version: 0.5.0
Summary: A simple and efficient web crawler in Python.
Home-page: http://github.com/indrajithi/tiny-web-crawler
License: GPL-3.0-or-later
Author: Indrajith Indraprastham
Author-email: indr4jith@gmail.com
Requires-Python: >=3.8,<4.0
Classifier: License :: OSI Approved :: GNU General Public License v3 or later (GPLv3+)
Classifier: Programming Language :: Python :: 3
Classifier: Programming Language :: Python :: 3.8
Classifier: Programming Language :: Python :: 3.9
Classifier: Programming Language :: Python :: 3.10
Classifier: Programming Language :: Python :: 3.11
Classifier: Programming Language :: Python :: 3.12
Requires-Dist: beautifulsoup4 (>=4.12.3,<5.0.0)
Requires-Dist: colorama (>=0.4.6,<0.5.0)
Requires-Dist: lxml (>=5.2.2,<6.0.0)
Requires-Dist: pylint (==3.0.2)
Requires-Dist: requests (>=2.32.3,<3.0.0)
Requires-Dist: validators (>=0.28.3,<0.29.0)
Project-URL: Documentation, http://github.com/indrajithi/tiny-web-crawler
Project-URL: Repository, http://github.com/indrajithi/tiny-web-crawler
